setup.py
mpathways_driver/__init__.py
mpathways_driver/driver.py
mpathways_driver/exceptions.py
mpathways_driver/helpers.py
mpathways_driver/listener.py
mpathways_driver.egg-info/PKG-INFO
mpathways_driver.egg-info/SOURCES.txt
mpathways_driver.egg-info/dependency_links.txt
mpathways_driver.egg-info/requires.txt
mpathways_driver.egg-info/top_level.txt