Metadata-Version: 1.0
Name: mpathways-driver
Version: 0.1.2
Summary: A wrapper around Selenium to enable automation in MPathways.
Home-page: https://github.com/jamie-r-davis/mpathways_driver
Author: Jamie Davis
Author-email: jamjam@umich.edu
License: MIT
Platform: UNKNOWN
